evoke/LICENSE
evoke/__init__.py
evoke/_version.py
evoke/core/__init__.py
evoke/core/client.py
evoke/core/config.py
evoke/core/session.py
evoke/core/system_info.py
evoke/core/transport.py
evoke/detection/__init__.py
evoke/detection/engine.py
evoke/detection/ml/__init__.py
evoke/detection/ml/classifier.py
evoke/detection/ml/models.py
evoke/detection/rules/__init__.py
evoke/detection/rules/base.py
evoke/detection/rules/injection.py
evoke/detection/rules/patterns.py
evoke/detection/rules/registry.py
evoke/functions/__init__.py
evoke/functions/analyze.py
evoke/functions/capture.py
evoke/functions/guard.py
evoke/functions/policy.py
evoke/schema/__init__.py
evoke/schema/detection.py
evoke/schema/entities.py
evoke/schema/events.py
evoke/schema/identity.py
evoke/schema/messages.py
evoke/schema/policy.py
evoke/schema/system_info.py
evoke/sync/__init__.py
evoke/sync/cache.py
evoke/sync/fetcher.py
evoke/sync/manager.py
evoke/sync/policy_cache.py
evoke/sync/policy_evaluator.py
evoke/sync/policy_fetcher.py
evoke/sync/policy_manager.py
evoke/sync/scheduler.py
evoke/wrappers/__init__.py
evoke/wrappers/anthropic.py
evoke/wrappers/base.py
evoke/wrappers/langchain.py
evoke/wrappers/litellm.py
evoke/wrappers/openai.py
evoke_sdk-0.1.0.dist-info/METADATA
evoke_sdk-0.1.0.dist-info/WHEEL
evoke_sdk-0.1.0.dist-info/RECORD
