Metadata-Version: 2.4
Name: evoke-sdk
Version: 0.1.0
Summary: AI Detection & Response SDK to monitor and protect agentic applications
License: Other/Proprietary License
Keywords: ai,llm,observability,security,openai,anthropic,langchain,langgraph,agents
Author: Evoke Security
Author-email: support@evokesecurity.com
Requires-Python: >=3.8,<4.0
Classifier: Development Status :: 4 - Beta
Classifier: Intended Audience :: Developers
Classifier: License :: Other/Proprietary License
Classifier: Operating System :: OS Independent
Classifier: Programming Language :: Python :: 3
Classifier: Programming Language :: Python :: 3.8
Classifier: Programming Language :: Python :: 3.9
Classifier: Programming Language :: Python :: 3.10
Classifier: Programming Language :: Python :: 3.11
Classifier: Programming Language :: Python :: 3.12
Classifier: Programming Language :: Python :: 3.13
Classifier: Programming Language :: Python :: 3.14
Classifier: Topic :: Security
Classifier: Topic :: Software Development :: Libraries :: Python Modules
Classifier: Topic :: System :: Monitoring
Provides-Extra: all
Provides-Extra: anthropic
Provides-Extra: langchain
Provides-Extra: openai
Requires-Dist: requests (>=2.28.0,<3.0.0)
Requires-Dist: wrapt (>=1.14.0,<2.0.0)
Project-URL: Documentation, https://app.evokesecurity.com/docs
Project-URL: Homepage, https://www.evokesecurity.com
Project-URL: Repository, https://github.com/evoke-security/evoke-sdk
